hello_package.py
hello_package-0.1.1.dist-info/LICENSE
hello_package-0.1.1.dist-info/METADATA
hello_package-0.1.1.dist-info/WHEEL
hello_package-0.1.1.dist-info/entry_points.txt
hello_package-0.1.1.dist-info/top_level.txt
hello_package-0.1.1.dist-info/RECORD
