Metadata-Version: 2.1
Name: hello-package
Version: 0.1.1
Summary: First package created by Phamduc
Home-page: UNKNOWN
Author: Pham Duc
License: UNKNOWN
Platform: UNKNOWN
Classifier: Programming Language :: Python :: 3
Classifier: License :: OSI Approved :: MIT License
Classifier: Operating System :: OS Independent
